corrected_fisher_randomization/__init__.py
corrected_fisher_randomization/cfr.py
corrected_fisher_randomization/test_run.py
corrected_fisher_randomization/utils.py
corrected_fisher_randomization-0.0.2.dist-info/LICENSE.txt
corrected_fisher_randomization-0.0.2.dist-info/METADATA
corrected_fisher_randomization-0.0.2.dist-info/WHEEL
corrected_fisher_randomization-0.0.2.dist-info/top_level.txt
corrected_fisher_randomization-0.0.2.dist-info/RECORD
